add_slash_command/__init__.py
add_slash_command-0.0.1.dist-info/METADATA
add_slash_command-0.0.1.dist-info/WHEEL
add_slash_command-0.0.1.dist-info/RECORD
